spfa/__init__.py
spfa/models/spFA.py
spfa/plots/__init__.py
spfa/plots/plots.py
spfa/utils/__init__.py
spfa/utils/utils.py
spfa-0.8.0.dist-info/WHEEL
spfa-0.8.0.dist-info/METADATA
spfa-0.8.0.dist-info/RECORD
